project_progress/__init__.py
project_progress/email_sending.py
project_progress/file_attachment.py
project_progress/reading_email_content.py
project_progress/reading_email_title.py
project_progress/send_notification.py
project_progress/slack_bot.py
project_progress/tests/test_all.py
project_2023-0.1.2.dist-info/LICENSE
project_2023-0.1.2.dist-info/METADATA
project_2023-0.1.2.dist-info/WHEEL
project_2023-0.1.2.dist-info/top_level.txt
project_2023-0.1.2.dist-info/RECORD
